django_baseline/template.py
django_baseline/views.py
django_baseline/tests.py
django_baseline/decorators.py
django_baseline/forms.py
django_baseline/models.py
django_baseline/address.py
django_baseline/__init__.py
django_baseline/html.py
django_baseline/static/baseline/baseline.css
django_baseline/static/baseline/baseline.js
django_baseline/static/baseline/js/jquery.serializeobject.js
django_baseline/static/baseline/js/django-ajax.js
django_baseline/static/baseline/js/countdown.js
django_baseline/static/baseline/css/forms.scss
django_baseline/templatetags/helpers.py
django_baseline/templatetags/__init__.py
django_baseline/templatetags/countdownbox.py
django_baseline/templates/crispy_form_raw.html
django_baseline/templates/crispy_form.html
django_baseline/templates/generics/delete.html
django_baseline/templates/generics/list.html
django_baseline/templates/generics/update_fieldsets.html
django_baseline/templates/generics/create_fieldsets.html
django_baseline/templates/generics/list_table.html
django_baseline/templates/generics/_formsets.html
django_baseline/templates/generics/detail.html
django_baseline/templates/generics/prompt.html
django_baseline/templates/generics/formsets_form.html
django_baseline/templates/generics/update.html
django_baseline/templates/generics/generic_edit.html
django_baseline/templates/generics/create.html
django_baseline/migrations/0001_initial.py
django_baseline/migrations/__init__.py
django_baseline-0.2.2.dist-info/DESCRIPTION.rst
django_baseline-0.2.2.dist-info/WHEEL
django_baseline-0.2.2.dist-info/pydist.json
django_baseline-0.2.2.dist-info/RECORD
django_baseline-0.2.2.dist-info/top_level.txt
django_baseline-0.2.2.dist-info/METADATA
utils/template.py
utils/views.py
utils/tests.py
utils/decorators.py
utils/forms.py
utils/models.py
utils/__init__.py
utils/html.py
utils/static/utils/utils.css
utils/static/utils/utils.js
utils/static/utils/js/jquery.serializeobject.js
utils/static/utils/js/django-ajax.js
utils/static/utils/js/countdown.js
utils/static/utils/css/forms.scss
utils/templatetags/helpers.py
utils/templatetags/helpers.pyc
utils/templatetags/__init__.pyc
utils/templatetags/__init__.py
utils/templatetags/countdownbox.py
